<!--服务器端发往客户端的信息格式-->
<!--游戏列表-->
<map>
	<entry>
		<key>gid</key>
		<value>6524584265821546</value>
		<key>show_name</key>
		<value>斗地主</value>
		<key>category</key>
		<value>10</value>
		<key>order</key>
		<value>2</value>
		<key>index_url</key>
		<value>www.baidu.com</value>
		<key>download_url</key>
		<value>www.baidu.com</value>
		<key>max_player</key>
		<value>4</value> 
		<key>min_player</key>
		<value>4</value>
	</entry>
	<entry>
		<key>gid</key>
		<value>2654859658412365</value>
		<key>show_name</key>
		<value>五子棋</value>
		<key>category</key>
		<value>11</value>
		<key>order</key>
		<value>0</value>
		<key>index_url</key>
		<value>www.baidu.com</value>
		<key>download_url</key>
		<value>www.baidu.com</value>
		<key>max_player</key>
		<value>2</value>
		<key>min_player</key>
		<value>2</value>
	</entry>
	<entry>
		<key>gid</key>
		<value>2654859695842365</value>
		<key>show_name</key>
		<value>飞行棋</value>
		<key>category</key>
		<value>11</value>
		<key>order</key>
		<value>1</value>
		<key>index_url</key>
		<value>www.baidu.com</value>
		<key>download_url</key>
		<value>www.baidu.com</value>
		<key>max_player</key>
		<value>4</value>
		<key>min_player</key>
		<value>2</value>
	</entry>
	<entry>
		<key>gid</key>
		<value>2654695455842365</value>
		<key>show_name</key>
		<value>坦克大战</value>
		<key>category</key>
		<value>20</value>
		<key>order</key>
		<value>0</value>
		<key>index_url</key>
		<value>www.baidu.com</value>
		<key>download_url</key>
		<value>www.baidu.com</value>
		<key>max_player</key>
		<value>10</value>
		<key>min_player</key>
		<value>2</value>
	</entry>
</map>
